ivhd/__init__.py
ivhd/ivhd.py
ivhd/ivhd_grad.py
ivhd-0.1.0.dist-info/LICENSE.md
ivhd-0.1.0.dist-info/METADATA
ivhd-0.1.0.dist-info/WHEEL
ivhd-0.1.0.dist-info/RECORD
